slh_dsa-0.2.0.dist-info/licenses/COPYING
slh_dsa-0.2.0.dist-info/licenses/COPYING.LESSER
slhdsa/__init__.py
slhdsa/exception.py
slhdsa/parameters.py
slhdsa/slhdsa.py
slhdsa/lowlevel/__init__.py
slhdsa/lowlevel/_utils.py
slhdsa/lowlevel/addresses.py
slhdsa/lowlevel/fors.py
slhdsa/lowlevel/hypertree.py
slhdsa/lowlevel/parameters.py
slhdsa/lowlevel/slhdsa.py
slhdsa/lowlevel/wots.py
slhdsa/lowlevel/xmss.py
tests/__init__.py
tests/test_a.py
tests/test_b.py
slh_dsa-0.2.0.dist-info/METADATA
slh_dsa-0.2.0.dist-info/WHEEL
slh_dsa-0.2.0.dist-info/top_level.txt
slh_dsa-0.2.0.dist-info/RECORD
