Metadata-Version: 2.4
Name: SLH-DSA
Version: 0.2.0
Summary: The pure python implement of the slh-dsa algorithm(based on fips205).
Home-page: https://github.com/colinxu2020/slhdsa
Author: Colinxu2020
Author-email: Colinxu2020 <colinxu2020@gmail.com>
License: LGPL-3.0-or-later
Project-URL: Homepage, https://github.com/colinxu2020/slhdsa
Project-URL: Bug Tracker, https://github.com/colinxu2020/slhdsa/issues
Keywords: fips205,slhdsa,sphincs,sphincsplus,crypto,cryptography
Classifier: Development Status :: 5 - Production/Stable
Classifier: Intended Audience :: Developers
Classifier: Topic :: Security
Classifier: Topic :: Security :: Cryptography
Classifier: Topic :: Software Development
Classifier: Topic :: Software Development :: Libraries
Classifier: Typing :: Typed
Classifier: License :: OSI Approved :: GNU Lesser General Public License v3 or later (LGPLv3+)
Classifier: Programming Language :: Python
Classifier: Programming Language :: Python :: 3
Classifier: Programming Language :: Python :: 3 :: Only
Classifier: Programming Language :: Python :: 3.9
Classifier: Programming Language :: Python :: 3.10
Classifier: Programming Language :: Python :: 3.11
Classifier: Programming Language :: Python :: 3.12
Classifier: Programming Language :: Python :: 3.13
Classifier: Programming Language :: Python :: 3.14
Classifier: Operating System :: OS Independent
Requires-Python: >=3.9
License-File: COPYING
License-File: COPYING.LESSER
Dynamic: author
Dynamic: home-page
Dynamic: license-file
Dynamic: requires-python
